LICENSE
MANIFEST.in
README.md
setup.cfg
setup.py
cloudwatch_metrics/__init__.py
cloudwatch_metrics/config.py
cloudwatch_metrics/metric_middleware.py
cloudwatch_metrics/metric_recorder.py
cloudwatch_metrics/metric_recorder_async.py
cloudwatch_metrics/units.py
cloudwatch_metrics/utils.py
cloudwatch_metrics/version.py
cloudwatch_metrics.egg-info/PKG-INFO
cloudwatch_metrics.egg-info/SOURCES.txt
cloudwatch_metrics.egg-info/dependency_links.txt
cloudwatch_metrics.egg-info/requires.txt
cloudwatch_metrics.egg-info/top_level.txt